dictionarify/__init__.py
dictionarify-0.0.12.dist-info/License
dictionarify-0.0.12.dist-info/METADATA
dictionarify-0.0.12.dist-info/WHEEL
dictionarify-0.0.12.dist-info/top_level.txt
dictionarify-0.0.12.dist-info/RECORD
