Metadata-Version: 2.1
Name: dictionarify
Version: 0.0.12
Summary: it is a class which have similar methods to list methods for dictionary
Author: Surya Narayanan K V
Author-email: githubsurya@gmail.com
Keywords: dictionary,dictionarify,flexi
Classifier: Programming Language :: Python :: 3
Classifier: License :: OSI Approved :: MIT License
Classifier: Operating System :: OS Independent
Requires-Python: >=3.7
License-File: License
